blender_id_oauth_client/__init__.py
blender_id_oauth_client/admin.py
blender_id_oauth_client/apps.py
blender_id_oauth_client/management/__init__.py
blender_id_oauth_client/management/commands/__init__.py
blender_id_oauth_client/management/commands/makesuperuser.py
blender_id_oauth_client/migrations/0001_initial.py
blender_id_oauth_client/migrations/0002_oauth_user_info.py
blender_id_oauth_client/migrations/0003_alter_oauthuserinfo_options.py
blender_id_oauth_client/migrations/0004_modify_oauth_user_id.py
blender_id_oauth_client/migrations/__init__.py
blender_id_oauth_client/models.py
blender_id_oauth_client/signals.py
blender_id_oauth_client/templates/blender_id_oauth_client/login_loop_detected.html
blender_id_oauth_client/urls.py
blender_id_oauth_client/views.py
blender_id_oauth_client-0.11.1.dist-info/LICENSE
blender_id_oauth_client-0.11.1.dist-info/METADATA
blender_id_oauth_client-0.11.1.dist-info/WHEEL
blender_id_oauth_client-0.11.1.dist-info/RECORD
